wikitable.py
wikitable-1.0.0.dist-info/LICENSE.txt
wikitable-1.0.0.dist-info/METADATA
wikitable-1.0.0.dist-info/WHEEL
wikitable-1.0.0.dist-info/top_level.txt
wikitable-1.0.0.dist-info/RECORD
