Metadata-Version: 2.1
Name: wikitable
Version: 1.0.0
Summary: Converts Wikipedia tables to dataframes and CSVs
Home-page: https://github.com/jaredmeyers/wikitable
Author: Jared Meyers
Author-email: jaredehren@verizon.net
License: UNKNOWN
Platform: UNKNOWN
Classifier: Programming Language :: Python :: 3
Classifier: Programming Language :: Python :: 3.6
Classifier: Programming Language :: Python :: 3.7
Classifier: License :: OSI Approved :: MIT License
Classifier: Operating System :: OS Independent
License-File: LICENSE.txt
Requires-Dist: requests
Requires-Dist: pandas
Requires-Dist: beautifulsoup4
Requires-Dist: lxml
Requires-Dist: html5lib
